odin_format/__init__.py
odin_format/formatter.py
odin_format-0.1.2.dist-info/METADATA
odin_format-0.1.2.dist-info/WHEEL
odin_format-0.1.2.dist-info/entry_points.txt
odin_format-0.1.2.dist-info/RECORD
