Metadata-Version: 2.1
Name: odin-format
Version: 0.1.2
Summary: 
Author: Alexandru Constantin Cardas
Requires-Python: >=3.10,<4.0
Classifier: Programming Language :: Python :: 3
Classifier: Programming Language :: Python :: 3.10
Classifier: Programming Language :: Python :: 3.11
Requires-Dist: autoflake (>=2.1.1,<3.0.0)
Requires-Dist: bandit (>=1.7.5,<2.0.0)
Requires-Dist: black (>=23.3.0,<24.0.0)
Requires-Dist: docformatter (>=1.6.5,<2.0.0)
Requires-Dist: flake8 (>=6.0.0,<7.0.0)
Requires-Dist: flake8-bugbear (>=23.5.9,<24.0.0)
Requires-Dist: isort (>=5.12.0,<6.0.0)
Requires-Dist: pydocstyle (>=6.3.0,<7.0.0)
Requires-Dist: pylint[spelling] (>=2.17.4,<3.0.0)
Requires-Dist: sourcery (>=1.2.0,<2.0.0)
